resin_release_tool/__init__.py
resin_release_tool/balena_backend.py
resin_release_tool/cli.py
resin_release_tool/releaser.py
resin_release_tool-0.3.2.dist-info/entry_points.txt
resin_release_tool-0.3.2.dist-info/LICENSE
resin_release_tool-0.3.2.dist-info/WHEEL
resin_release_tool-0.3.2.dist-info/METADATA
resin_release_tool-0.3.2.dist-info/RECORD
