Metadata-Version: 2.1
Name: resin-release-tool
Version: 0.3.2
Summary: Release tool to have canary in resin.io
Home-page: https://github.com/mobilityhouse/resin-release-tool
License: MIT
Keywords: resin,deploy
Author: roger
Author-email: roger.duran@mobilityhouse.com
Requires-Python: >=3.9,<4.0
Classifier: License :: OSI Approved :: MIT License
Classifier: Programming Language :: Python :: 3
Classifier: Programming Language :: Python :: 3.9
Classifier: Programming Language :: Python :: 3.10
Classifier: Programming Language :: Python :: 3.11
Requires-Dist: balena-sdk (>=11.2.0,<12.0.0)
Requires-Dist: click (>=8.0.0,<9.0.0)
